LICENSE
pocketsnack/__init__.py
pocketsnack/pocketsnack.py
pocketsnack/toolkit.py
pocketsnack-3.2.1.dist-info/entry_points.txt
pocketsnack-3.2.1.dist-info/LICENSE
pocketsnack-3.2.1.dist-info/WHEEL
pocketsnack-3.2.1.dist-info/METADATA
pocketsnack-3.2.1.dist-info/RECORD
