Metadata-Version: 2.1
Name: pocketsnack
Version: 3.2.1
Summary: KonMari your Pocket tsundoku from the command line
Home-page: https://github.com/hughrun/pocketsnack
License: GPL-3.0-or-later
Keywords: pocket,api
Author: Hugh Rundle
Author-email: hugh@hughrundle.net
Requires-Python: >=3.6.1,<4.0.0
Classifier: Environment :: Console
Classifier: License :: OSI Approved :: GNU General Public License v3 or later (GPLv3+)
Classifier: Operating System :: OS Independent
Classifier: Programming Language :: Python :: 3
Classifier: Programming Language :: Python :: 3.7
Classifier: Programming Language :: Python :: 3.8
Classifier: Programming Language :: Python :: 3.9
Classifier: Topic :: Utilities
Requires-Dist: argparse (>=1.4.0,<2.0.0)
Requires-Dist: pyyaml (>=5.4.1,<6.0.0)
Requires-Dist: requests (>=2.25.1,<3.0.0)
Requires-Dist: rich (>=9.10.0,<10.0.0)
Project-URL: Repository, https://github.com/hughrun/pocketsnack
